README.rst
setup.py
django_payone/__init__.py
django_payone/connection.py
django_payone/exceptions.py
django_payone/models.py
django_payone/settings.py
django_payone/tests.py
django_payone/views.py
django_payone.egg-info/PKG-INFO
django_payone.egg-info/SOURCES.txt
django_payone.egg-info/dependency_links.txt
django_payone.egg-info/top_level.txt
django_payone/channel/__init__.py
django_payone/channel/client.py
django_payone/channel/server.py
django_payone/static/payone/client.js